dadi_cli/BestFit.py
dadi_cli/GenerateCache.py
dadi_cli/GenerateFs.py
dadi_cli/InferDFE.py
dadi_cli/InferDM.py
dadi_cli/Models.py
dadi_cli/Pdfs.py
dadi_cli/Plot.py
dadi_cli/SimulateFs.py
dadi_cli/Stat.py
dadi_cli/__init__.py
dadi_cli/__main__.py
dadi_cli/utilities.py
dadi_cli/parsers/__init__.py
dadi_cli/parsers/argument_validation.py
dadi_cli/parsers/bestfit_parsers.py
dadi_cli/parsers/common_arguments.py
dadi_cli/parsers/generate_cache_parsers.py
dadi_cli/parsers/generate_fs_parsers.py
dadi_cli/parsers/infer_dfe_parsers.py
dadi_cli/parsers/infer_dm_parsers.py
dadi_cli/parsers/model_parsers.py
dadi_cli/parsers/pdf_parsers.py
dadi_cli/parsers/plot_parsers.py
dadi_cli/parsers/simulate_demes_parsers.py
dadi_cli/parsers/simulate_dfe_parsers.py
dadi_cli/parsers/simulate_dm_parsers.py
dadi_cli/parsers/stat_dfe_parsers.py
dadi_cli/parsers/stat_dm_parsers.py
dadi_cli-0.9.13.dist-info/METADATA
dadi_cli-0.9.13.dist-info/WHEEL
dadi_cli-0.9.13.dist-info/entry_points.txt
dadi_cli-0.9.13.dist-info/licenses/LICENSE
dadi_cli-0.9.13.dist-info/RECORD
