Metadata-Version: 2.4
Name: dadi-cli
Version: 0.9.13
Summary: A command line interface for dadi
Project-URL: Homepage, https://github.com/xin-huang/dadi-cli
Author-email: Xin Huang <xinhuang.res@gmail.com>
License-Expression: Apache-2.0
License-File: LICENSE
Classifier: License :: OSI Approved :: Apache Software License
Classifier: Programming Language :: Python
Classifier: Programming Language :: Python :: 3.9
Requires-Python: >=3.9
Requires-Dist: dadi>=2.4.3
